konashi/Errors.py
konashi/Konashi.py
konashi/KonashiElementBase.py
konashi/__init__.py
konashi/Builtin/AccelGyro.py
konashi/Builtin/Humidity.py
konashi/Builtin/Presence.py
konashi/Builtin/Pressure.py
konashi/Builtin/RGBLed.py
konashi/Builtin/Temperature.py
konashi/Builtin/__init__.py
konashi/Io/AIO.py
konashi/Io/GPIO.py
konashi/Io/HardPWM.py
konashi/Io/I2C.py
konashi/Io/SPI.py
konashi/Io/SoftPWM.py
konashi/Io/UART.py
konashi/Io/__init__.py
konashi/Settings/Bluetooth.py
konashi/Settings/System.py
konashi/Settings/__init__.py
konashi-0.4.1.dist-info/LICENSE
konashi-0.4.1.dist-info/METADATA
konashi-0.4.1.dist-info/WHEEL
konashi-0.4.1.dist-info/top_level.txt
konashi-0.4.1.dist-info/RECORD
