Metadata-Version: 2.1
Name: konashi
Version: 0.4.1
Summary: Konashi SDK for Python3
Author-email: Sebastian MILLER <sebastian@ux-xu.com>
License: MIT License
Project-URL: repository, https://github.com/YUKAI/konashi5-sdk-python
Project-URL: bug-tracker, https://github.com/YUKAI/konashi5-sdk-python/issues
Keywords: konashi,Koshian,BLE,Bluetooth
Classifier: Programming Language :: Python :: 3
Classifier: License :: OSI Approved :: MIT License
Classifier: Operating System :: OS Independent
Requires-Python: >=3.8
License-File: LICENSE
Requires-Dist: bleak (<0.15.0,>=0.10.0)
